README.rst
setup.py
vertica_locust_client/__init__.py
vertica_locust_client/client.py
vertica_locust_client/user.py
vertica_locust_client.egg-info/PKG-INFO
vertica_locust_client.egg-info/SOURCES.txt
vertica_locust_client.egg-info/dependency_links.txt
vertica_locust_client.egg-info/not-zip-safe
vertica_locust_client.egg-info/requires.txt
vertica_locust_client.egg-info/top_level.txt