Metadata-Version: 1.2
Name: vertica-locust-client
Version: 0.0.3
Summary: A Vertica client for use with the locust.io load testing tool
Home-page: UNKNOWN
Author: Matt Spilchen
Author-email: matt.spilchen@vertica.com
License: Apache License, Version 2.0
Platform: UNKNOWN
Classifier: Development Status :: 4 - Beta
Classifier: Intended Audience :: Developers
Classifier: License :: OSI Approved :: Apache Software License
Classifier: Programming Language :: Python :: 3
Requires-Python: >=3
